unfold/__init__.py
unfold/admin.py
unfold/apps.py
unfold/checks.py
unfold/components.py
unfold/contrib/__init__.py
unfold/contrib/filters/__init__.py
unfold/contrib/filters/admin/__init__.py
unfold/contrib/filters/admin/autocomplete_filters.py
unfold/contrib/filters/admin/choice_filters.py
unfold/contrib/filters/admin/datetime_filters.py
unfold/contrib/filters/admin/dropdown_filters.py
unfold/contrib/filters/admin/mixins.py
unfold/contrib/filters/admin/numeric_filters.py
unfold/contrib/filters/admin/text_filters.py
unfold/contrib/filters/apps.py
unfold/contrib/filters/forms.py
unfold/contrib/filters/static/unfold/filters/css/nouislider/LICENSE
unfold/contrib/filters/static/unfold/filters/css/nouislider/nouislider.min.css
unfold/contrib/filters/static/unfold/filters/js/DateTimeShortcuts.js
unfold/contrib/filters/static/unfold/filters/js/admin-numeric-filter.js
unfold/contrib/filters/static/unfold/filters/js/nouislider/LICENSE
unfold/contrib/filters/static/unfold/filters/js/nouislider/nouislider.min.js
unfold/contrib/filters/static/unfold/filters/js/wnumb/LICENSE
unfold/contrib/filters/static/unfold/filters/js/wnumb/wNumb.min.js
unfold/contrib/filters/templates/unfold/filters/filters_date_range.html
unfold/contrib/filters/templates/unfold/filters/filters_datetime_range.html
unfold/contrib/filters/templates/unfold/filters/filters_field.html
unfold/contrib/filters/templates/unfold/filters/filters_numeric_range.html
unfold/contrib/filters/templates/unfold/filters/filters_numeric_single.html
unfold/contrib/filters/templates/unfold/filters/filters_numeric_slider.html
unfold/contrib/forms/__init__.py
unfold/contrib/forms/apps.py
unfold/contrib/forms/static/unfold/forms/css/trix/LICENSE
unfold/contrib/forms/static/unfold/forms/css/trix/trix.css
unfold/contrib/forms/static/unfold/forms/js/trix/LICENSE
unfold/contrib/forms/static/unfold/forms/js/trix/trix.js
unfold/contrib/forms/static/unfold/forms/js/trix.config.js
unfold/contrib/forms/templates/unfold/forms/array.html
django_unfold-1.0.0.dist-info/LICENSE.md
django_unfold-1.0.0.dist-info/METADATA
django_unfold-1.0.0.dist-info/WHEEL
django_unfold-1.0.0.dist-info/RECORD
