Metadata-Version: 2.3
Name: django-unfold
Version: 1.0.0
Summary: Modern Django admin theme for seamless interface development
License: MIT
Keywords: django,admin,tailwind,theme
Requires-Python: >=3.9
Classifier: Environment :: Web Environment
Classifier: Framework :: Django
Classifier: Intended Audience :: Developers
Classifier: License :: OSI Approved :: MIT License
Classifier: Operating System :: OS Independent
Classifier: Programming Language :: Python
Classifier: Programming Language :: Python :: 3
Classifier: Programming Language :: Python :: 3.9
Classifier: Programming Language :: Python :: 3.10
Classifier: Programming Language :: Python :: 3.11
Classifier: Programming Language :: Python :: 3.12
Classifier: Programming Language :: Python :: 3.13
Requires-Dist: django (>=4.2)
Project-URL: Homepage, https://unfoldadmin.com
Project-URL: Repository, https://github.com/unfoldadmin/django-unfold
